jiraservicemanagement/__init__.py
jiraservicemanagement/api/__init__.py
jiraservicemanagement/api/v1.py
jsm_python_api-0.1.dist-info/LICENSE
jsm_python_api-0.1.dist-info/METADATA
jsm_python_api-0.1.dist-info/WHEEL
jsm_python_api-0.1.dist-info/top_level.txt
jsm_python_api-0.1.dist-info/RECORD
