Metadata-Version: 2.1
Name: jsm-python-api
Version: 0.1
Summary: Python bindings for Jira Service Management API
Home-page: https://github.com/stanislavulrych/jsm-python-api
Author: Stanislav Ulrych
Author-email: stanislav.ulrych@gmail.com
Project-URL: Bug Tracker, https://github.com/stanislavulrych/jsm-python-api/issues
Classifier: Programming Language :: Python :: 3
Classifier: License :: OSI Approved :: Apache Software License
Classifier: Operating System :: OS Independent
Requires-Python: >=3.10.11
License-File: LICENSE
